statsforegyptian/__init__.py
statsforegyptian/main.py
statsforegyptian-0.1.2.dist-info/METADATA
statsforegyptian-0.1.2.dist-info/WHEEL
statsforegyptian-0.1.2.dist-info/top_level.txt
statsforegyptian-0.1.2.dist-info/RECORD
