Metadata-Version: 2.1
Name: statsforegyptian
Version: 0.1.2
Author: Mohamed Habashy Hussein
